CYB600_Lab1-1.0.2.data/scripts/telltime
cyb600_lab1/__init__.py
cyb600_lab1/main.py
CYB600_Lab1-1.0.2.dist-info/LICENSE
CYB600_Lab1-1.0.2.dist-info/METADATA
CYB600_Lab1-1.0.2.dist-info/WHEEL
CYB600_Lab1-1.0.2.dist-info/top_level.txt
CYB600_Lab1-1.0.2.dist-info/RECORD
