Metadata-Version: 2.1
Name: CYB600-Lab1
Version: 1.0.2
Summary: CYB600 Lab 1 Webserver
Home-page: UNKNOWN
Author: Jacob Smith
Author-email: smith542@my.canisius.edu
License: Apache License Version 2.0
Platform: UNKNOWN
License-File: LICENSE
